kamunu/Kamunu.py
kamunu/__init__.py
kamunu/_version.py
kamunu/cat_scrapper.py
kamunu/db.py
kamunu/enrichment.py
kamunu/extract_data.py
kamunu/id_input.py
kamunu/kamunu_main.py
kamunu/local_search.py
kamunu/utils/wiki_ids.py
kamunu-0.0.3a0.data/scripts/kamunu_run
kamunu-0.0.3a0.dist-info/METADATA
kamunu-0.0.3a0.dist-info/WHEEL
kamunu-0.0.3a0.dist-info/top_level.txt
kamunu-0.0.3a0.dist-info/RECORD
