Metadata-Version: 2.1
Name: kamunu
Version: 0.0.3a0
Summary: A package for searching organization identifiers in multiple search engines.
Home-page: https://github.com/colav-playground/kamunu/
Author: Colav
Author-email: colav@udea.edu.co
License: BSD
Requires-Python: >3.6
Requires-Dist: pymongo
Requires-Dist: requests
Requires-Dist: beautifulsoup4
Requires-Dist: langdetect
Requires-Dist: fuzzywuzzy
Requires-Dist: python-Levenshtein
Requires-Dist: unidecode
Requires-Dist: deep-translator
Requires-Dist: translators
Requires-Dist: nltk
Requires-Dist: html5lib
Requires-Dist: pycountry
